datasail/__init__.py
datasail/__main__.py
datasail/argparse_patch.py
datasail/args/cdhit.yaml
datasail/args/cdhit_est.yaml
datasail/args/diamond.yaml
datasail/args/foldseek.yaml
datasail/args/mash.yaml
datasail/args/mash_dist.yaml
datasail/args/mash_sketch.yaml
datasail/args/mmseqs2.yaml
datasail/args/mmseqspp.yaml
datasail/cluster/__init__.py
datasail/cluster/caching.py
datasail/cluster/cdhit.py
datasail/cluster/cdhit_est.py
datasail/cluster/clustering.py
datasail/cluster/diamond.py
datasail/cluster/ecfp.py
datasail/cluster/foldseek.py
datasail/cluster/mash.py
datasail/cluster/mmseqs2.py
datasail/cluster/mmseqspp.py
datasail/cluster/tmalign.py
datasail/cluster/utils.py
datasail/cluster/vectors.py
datasail/cluster/wlk.py
datasail/eval.py
datasail/parsers.py
datasail/reader/__init__.py
datasail/reader/read.py
datasail/reader/read_genomes.py
datasail/reader/read_molecules.py
datasail/reader/read_other.py
datasail/reader/read_proteins.py
datasail/reader/utils.py
datasail/reader/validate.py
datasail/report.py
datasail/routine.py
datasail/sail.py
datasail/settings.py
datasail/solver/__init__.py
datasail/solver/cluster_1d.py
datasail/solver/cluster_2d.py
datasail/solver/id_1d.py
datasail/solver/id_2d.py
datasail/solver/overflow.py
datasail/solver/solve.py
datasail/solver/utils.py
datasail/version.py
datasail-1.3.0.dist-info/METADATA
datasail-1.3.0.dist-info/WHEEL
datasail-1.3.0.dist-info/entry_points.txt
datasail-1.3.0.dist-info/licenses/LICENSE
datasail-1.3.0.dist-info/RECORD
