Metadata-Version: 2.4
Name: datasail
Version: 1.3.0
Summary: A package to compute hard out-of-distribution data splits for machine learning, challenging generalization of models.
License-File: LICENSE
Author: Roman Joeres
Author-email: roman.joeres@helmholtz-hips.de
Requires-Python: >=3.9,<3.13.0
Classifier: Development Status :: 5 - Production/Stable
Classifier: License :: OSI Approved :: MIT License
Classifier: Operating System :: OS Independent
Classifier: Programming Language :: Python :: 3
Classifier: Programming Language :: Python :: 3.9
Classifier: Programming Language :: Python :: 3.10
Classifier: Programming Language :: Python :: 3.11
Classifier: Programming Language :: Python :: 3.12
Requires-Dist: cvxopt
Requires-Dist: cvxpy (==1.5.3)
Requires-Dist: grakel (<0.1.10)
Requires-Dist: h5py
Requires-Dist: importlib_resources
Requires-Dist: matplotlib
Requires-Dist: networkx
Requires-Dist: numpy (<2)
Requires-Dist: pandas
Requires-Dist: pyarrow
Requires-Dist: pyscipopt
Requires-Dist: pyyaml
Requires-Dist: rdkit
Requires-Dist: scikit-learn
Requires-Dist: scip (<=9.1)
Requires-Dist: tqdm
Project-URL: Repository, https://github.com/kalininalab/DataSAIL
